biocircuits/__init__.py
biocircuits/dynsys.py
biocircuits/gillespie.py
biocircuits/jsfunctions.py
biocircuits/jsplots.py
biocircuits/rd.py
biocircuits/reg.py
biocircuits/test.py
biocircuits/test2.py
biocircuits/utils.py
biocircuits/vignettes.py
biocircuits/viz.py
biocircuits/apps/__init__.py
biocircuits/apps/ffl.py
biocircuits/apps/ffl_app.py
biocircuits/apps/promiscuous.py
biocircuits/apps/promiscuous_app.py
biocircuits-0.1.14.dist-info/LICENSE.md
biocircuits-0.1.14.dist-info/METADATA
biocircuits-0.1.14.dist-info/WHEEL
biocircuits-0.1.14.dist-info/top_level.txt
biocircuits-0.1.14.dist-info/RECORD
