Metadata-Version: 2.1
Name: biocircuits
Version: 0.1.14
Summary: Utilities to accompany *Biological Circuit Design* by Michael Elowitz and Justin Bois.
Home-page: https://github.com/justinbois/biocircuits
Download-URL: https://github.com/justinbois/biocircuits/tarball/0.1.14
Author: Justin Bois
Author-email: bois@caltech.edu
License: BSD
Classifier: Development Status :: 3 - Alpha
Classifier: Intended Audience :: Developers
Classifier: Programming Language :: Python :: 3
License-File: LICENSE.md
Requires-Dist: numpy
Requires-Dist: scipy
Requires-Dist: pandas
Requires-Dist: numba
Requires-Dist: tqdm
Requires-Dist: multiprocess
Requires-Dist: bokeh
Requires-Dist: matplotlib
Requires-Dist: colorcet
Requires-Dist: eqtk
